{"name":"迭代器","slug":"迭代器","count":1,"postlist":[{"title":"迭代器","uid":"5391af7718199d3c4ba5b2fd9250437c","slug":"迭代器","date":"2021-05-04T18:15:50.000Z","updated":"2024-05-16T19:47:08.737Z","comments":true,"path":"api/articles/迭代器.json","keywords":null,"cover":null,"text":"当我们要遍历容器如vector,map等复杂结构时，可以通过迭代器进行遍历，依次取出容器中的值。通过容器类的begin()和end()函数获取指向第一个元素位置的迭代器和指向最后一个元素下一个位置的迭代器。 迭代器初步使用...","permalink":"/post/迭代器","photos":[],"count_time":{"symbolsCount":"3.7k","symbolsTime":"3 mins."},"categories":[{"name":"C++基础","slug":"C-基础","count":7,"path":"api/categories/C-基础.json"}],"tags":[{"name":"C++","slug":"C","count":7,"path":"api/tags/C.json"},{"name":"迭代器","slug":"迭代器","count":1,"path":"api/tags/迭代器.json"}],"author":{"name":"kiyose408","slug":"blog-author","avatar":"img/kiyose.png","link":"/","description":"强风吹拂~","socials":{"github":"https://github.com/kiyose408","twitter":"","stackoverflow":"https://stackoverflow.com/users/22586365/kiyose408","wechat":"","qq":"","weibo":"","zhihu":"","csdn":"https://blog.csdn.net/qq_4492248","juejin":"https://juejin.cn/user/3941068096931262","customs":{"gitee":{"icon":"/svg/gitee.svg","link":"https://gitee.com/kiyose408"}}}},"feature":true}]}